zho_tts/__init__.py
zho_tts/cn_tn.py
zho_tts/globals.py
zho_tts/helper.py
zho_tts/io.py
zho_tts/py.typed
zho_tts/resources.py
zho_tts/synthesizer.py
zho_tts/transcriber.py
zho_tts_app/__init__.py
zho_tts_app/app.py
zho_tts_app/globals.py
zho_tts_app/logging_configuration.py
zho_tts_app/main.py
zho_tts_app/py.typed
zho_tts_cli/__init__.py
zho_tts_cli/argparse_helper.py
zho_tts_cli/cli.py
zho_tts_cli/main.py
zho_tts_cli/py.typed
zho_tts_gr/__init__.py
zho_tts_gr/app.py
zho_tts_gr/py.typed
zho_tts-0.0.2.dist-info/LICENSE
zho_tts-0.0.2.dist-info/METADATA
zho_tts-0.0.2.dist-info/WHEEL
zho_tts-0.0.2.dist-info/entry_points.txt
zho_tts-0.0.2.dist-info/top_level.txt
zho_tts-0.0.2.dist-info/RECORD
