Metadata-Version: 2.1
Name: zho-tts
Version: 0.0.2
Summary: Web app, command-line interface and Python library for synthesizing Chinese texts into speech.
Author-email: Stefan Taubert <pypi@stefantaubert.com>
Maintainer-email: Stefan Taubert <pypi@stefantaubert.com>
License: MIT
Project-URL: Homepage, https://github.com/stefantaubert/zh-tts
Project-URL: Issues, https://github.com/stefantaubert/zh-tts/issues
Keywords: Text-to-speech,Speech synthesis,praat,TextGrid,Utils,Language,Linguistics
Classifier: Development Status :: 2 - Pre-Alpha
Classifier: Operating System :: OS Independent
Classifier: Operating System :: MacOS
Classifier: Operating System :: POSIX
Classifier: Operating System :: POSIX :: BSD
Classifier: Operating System :: POSIX :: Linux
Classifier: Operating System :: Unix
Classifier: Operating System :: Microsoft :: Windows
Classifier: Programming Language :: Python
Classifier: Programming Language :: Python :: 3
Classifier: Programming Language :: Python :: 3.8
Classifier: Programming Language :: Python :: 3.9
Classifier: Programming Language :: Python :: 3.10
Classifier: Programming Language :: Python :: 3.11
Classifier: License :: OSI Approved :: MIT License
Requires-Python: <3.12,>=3.8
License-File: LICENSE
Requires-Dist: numpy >=1.18.5
Requires-Dist: tqdm >=4.63.0
Requires-Dist: ordered-set >=4.1.0
Requires-Dist: ffmpy >=0.3.1
Requires-Dist: spacy-pkuseg >=0.0.33
Requires-Dist: zhon >=2.0.2
Requires-Dist: opencc-py >=1.1.0
Requires-Dist: torch >=2.0.0
Requires-Dist: pronunciation-dictionary >=0.0.6
Requires-Dist: pronunciation-dictionary-utils >=0.0.5
Requires-Dist: dict-from-dict >=0.0.4
Requires-Dist: dict-from-pypinyin >=0.0.2
Requires-Dist: tacotron-cli >=0.0.5
Requires-Dist: waveglow-cli >=0.0.2
Requires-Dist: txt-utils >=0.0.3
Requires-Dist: pinyin-to-ipa >=0.0.2
Requires-Dist: gradio[oauth] >=4.26.0
Requires-Dist: uvicorn >=0.14.0
